README.md
setup.cfg
setup.py
usafe.py
scripts/usafe-a
usafe.egg-info/PKG-INFO
usafe.egg-info/SOURCES.txt
usafe.egg-info/dependency_links.txt
usafe.egg-info/requires.txt
usafe.egg-info/top_level.txt