Metadata-Version: 1.1
Name: usafe
Version: 0.1.1
Summary: oversimplistic secret data storage with cryptography protection
Home-page: http://github.com/bobuk/usafe
Author: Grigory Bakunov
Author-email: thebobuk@ya.ru
License: UNKNOWN
Platform: UNKNOWN
Classifier: Programming Language :: Python
Classifier: Programming Language :: Python :: 3
Classifier: Development Status :: 4 - Beta
Classifier: Environment :: Other Environment
Classifier: Intended Audience :: Developers
Classifier: Operating System :: OS Independent
Classifier: Topic :: Software Development :: Libraries :: Python Modules
